<?xml version="1.0"?>
<opencv_storage>
<obj>
  <_><id>1</id>
    <height>1.1645561456680298e-01</height>
    <contour2d>
      5.44445276e-01 1.88664123e-02 5.14685273e-01 2.44327225e-02
      5.13686419e-01 2.44821887e-02 5.05750418e-01 2.02617198e-02
      5.05767226e-01 1.76116358e-02 5.09443164e-01 -3.30734998e-02
      5.11553407e-01 -3.48075032e-02 5.14259696e-01 -3.50518040e-02
      5.39938927e-01 -3.42723317e-02 5.43157816e-01 -3.30552608e-02
      5.46983004e-01 -3.05717066e-02 5.48610687e-01 -1.92649290e-03
      5.46709776e-01 1.24099115e-02 5.45478582e-01 1.62748061e-02</contour2d>
    <histogram type_id="opencv-matrix">
      <rows>20</rows>
      <cols>1</cols>
      <dt>f</dt>
      <data>
        3.70370373e-02 4.36081216e-02 3.46475504e-02 3.58422939e-03 0.
        0. 0. 0. 0. 0. 0. 2.38948618e-03 2.92712059e-02 6.33213818e-02
        1.60692945e-01 2.63440847e-01 1.51134998e-01 4.24133800e-02 0.
        1.68458775e-01</data></histogram></_>
  <_><id>2</id>
    <height>1.1563390493392944e-01</height>
    <contour2d>
      5.30536175e-01 2.94146687e-02 5.29452682e-01 2.94080153e-02
      5.24573922e-01 2.80879606e-02 5.22691905e-01 2.68223155e-02
      5.04184961e-01 -1.61208902e-02 5.03237188e-01 -2.37542726e-02
      5.03936291e-01 -2.58963443e-02 5.05028605e-01 -2.86371056e-02
      5.09368539e-01 -3.19205076e-02 5.23903012e-01 -3.50040756e-02
      5.29320419e-01 -3.53995748e-02 5.31321645e-01 -3.41038816e-02
      5.34319580e-01 -3.15186195e-02 5.40677309e-01 -2.13438496e-02
      5.44055462e-01 -1.49681559e-02 5.51057696e-01 6.25714776e-04
      5.52656293e-01 5.86310728e-03 5.52631974e-01 9.78615228e-03
      5.52007139e-01 1.23855462e-02</contour2d>
    <histogram type_id="opencv-matrix">
      <rows>20</rows>
      <cols>1</cols>
      <dt>f</dt>
      <data>
        4.52127643e-02 4.85372320e-02 2.59308498e-02 4.65425523e-03
        1.32978719e-03 0. 0. 0. 0. 0. 0. 0. 1.39627652e-02
        9.77393612e-02 1.76196799e-01 3.15824449e-01 1.13031909e-01
        3.65691483e-02 0. 1.21010631e-01</data></histogram></_>
  <_><id>3</id>
    <height>1.1564970016479492e-01</height>
    <contour2d>
      5.59943914e-01 -1.03824083e-02 5.59872627e-01 -1.16797024e-03
      5.55687189e-01 1.06039401e-02 5.50845027e-01 2.18448378e-02
      5.48962414e-01 2.33959127e-02 5.46615124e-01 2.32314598e-02
      5.02282858e-01 6.33144099e-03 5.06361783e-01 -1.07936431e-02
      5.14140785e-01 -3.08140852e-02 5.16695201e-01 -3.17832045e-02
      5.17688930e-01 -3.17755789e-02 5.39905488e-01 -2.32275873e-02
      5.45746982e-01 -2.06938051e-02 5.55062652e-01 -1.56077407e-02
      5.57903409e-01 -1.30309425e-02</contour2d>
    <histogram type_id="opencv-matrix">
      <rows>20</rows>
      <cols>1</cols>
      <dt>f</dt>
      <data>
        1.32075474e-02 1.69811323e-02 5.66037744e-03 3.77358496e-03 0.
        0. 0. 0. 0. 0. 0. 2.83018872e-03 1.50943398e-02 7.64150918e-02
        2.16037735e-01 2.73584902e-01 1.17924526e-01 2.45283023e-02 0.
        2.33962268e-01</data></histogram></_>
  <_><id>4</id>
    <height>1.1421048641204834e-01</height>
    <contour2d>
      5.57918727e-01 1.32600321e-02 5.19212067e-01 2.02099178e-02
      5.16528428e-01 2.02521216e-02 5.12337565e-01 1.76944844e-02
      5.09079635e-01 -1.08687878e-02 5.08698583e-01 -1.68602839e-02
      5.09182930e-01 -2.19626296e-02 5.11299193e-01 -2.28471030e-02
      5.29638946e-01 -2.58153807e-02 5.53312659e-01 -2.59924103e-02
      5.56139708e-01 -2.21566223e-02 5.58755994e-01 -1.56063987e-02
      5.59753239e-01 -1.16598783e-02 5.60872555e-01 2.78799445e-03
      5.60842037e-01 6.73704688e-03 5.59580684e-01 1.06591042e-02</contour2d>
    <histogram type_id="opencv-matrix">
      <rows>20</rows>
      <cols>1</cols>
      <dt>f</dt>
      <data>
        1.93370171e-02 1.65745858e-02 9.20810364e-03 0. 0. 0. 0. 0. 0.
        0. 9.20810329e-04 9.20810329e-04 4.60405182e-03 5.70902415e-02
        1.87845305e-01 3.05709034e-01 1.54696137e-01 5.52486181e-02 0.
        1.87845305e-01</data></histogram></_>
  <_><id>5</id>
    <height>1.1568933725357056e-01</height>
    <contour2d>
      5.47183275e-01 -3.41433175e-02 5.53272784e-01 -2.67758165e-02
      5.62004864e-01 -1.37969479e-02 5.65272331e-01 -8.54224805e-03
      5.65264106e-01 -7.22237676e-03 5.62969804e-01 -3.25966324e-03
      5.56738079e-01 4.60045645e-03 5.31626403e-01 2.96318084e-02
      5.18582106e-01 2.88201012e-02 5.16733170e-01 2.73546297e-02
      5.06231904e-01 -4.77071153e-03 5.06239951e-01 -6.06106082e-03
      5.06702244e-01 -7.33475760e-03 5.13125360e-01 -1.35134840e-02
      5.30510962e-01 -2.93547623e-02 5.42825699e-01 -3.33745778e-02
      5.46099782e-01 -3.41499932e-02</contour2d>
    <histogram type_id="opencv-matrix">
      <rows>20</rows>
      <cols>1</cols>
      <dt>f</dt>
      <data>
        5.92913963e-02 1.95227768e-02 7.23065808e-03 0. 0. 0. 0. 0. 0.
        0. 0. 7.23065808e-04 9.39985551e-03 4.41070125e-02
        1.14967465e-01 1.87274039e-01 1.67751268e-01 1.40274763e-01 0.
        2.49457702e-01</data></histogram></_>
  <_><id>6</id>
    <height>1.1559176445007324e-01</height>
    <contour2d>
      5.62029004e-01 -1.77570321e-02 5.62012732e-01 -1.51243387e-02
      5.56960821e-01 4.58545657e-03 5.45853317e-01 2.26650257e-02
      5.37335277e-01 2.89599877e-02 5.35315216e-01 2.89475843e-02
      5.30156136e-01 2.77909786e-02 5.23054302e-01 2.51492821e-02
      5.15422821e-01 2.01328862e-02 5.11803627e-01 1.45148328e-02
      5.11835337e-01 9.39524174e-03 5.19007206e-01 -1.61596667e-02
      5.19439459e-01 -1.74092464e-02 5.30665040e-01 -3.07532977e-02
      5.34740567e-01 -3.29814069e-02 5.38299859e-01 -3.28266583e-02</contour2d>
    <histogram type_id="opencv-matrix">
      <rows>20</rows>
      <cols>1</cols>
      <dt>f</dt>
      <data>
        7.80051127e-02 3.32480818e-02 1.27877239e-02 0. 0. 0. 0. 0. 0.
        0. 1.27877237e-03 5.75447548e-03 1.27877239e-02 4.92327362e-02
        1.46419436e-01 1.64322242e-01 1.38746798e-01 1.40664965e-01 0.
        2.16751918e-01</data></histogram></_>
  <_><id>7</id>
    <height>1.1474633216857910e-01</height>
    <contour2d>
      5.47166288e-01 -2.53275614e-02 5.48781276e-01 -2.40566786e-02
      5.50983667e-01 -1.89058445e-02 5.52160919e-01 -1.24274930e-02
      5.52136660e-01 -8.50965548e-03 5.50781846e-01 1.36560295e-02
      5.49713850e-01 2.14646272e-02 5.47450423e-01 2.65981145e-02
      5.17254114e-01 2.96883080e-02 5.16260386e-01 2.96822060e-02
      5.14967918e-01 -1.10646645e-02 5.15178263e-01 -2.36809496e-02
      5.17333865e-01 -2.50152387e-02 5.21657109e-01 -2.69707125e-02
      5.35889030e-01 -2.64151338e-02</contour2d>
    <histogram type_id="opencv-matrix">
      <rows>20</rows>
      <cols>1</cols>
      <dt>f</dt>
      <data>
        4.66491431e-02 2.62812078e-02 6.57030195e-03 6.57030207e-04 0.
        0. 0. 0. 0. 0. 0. 2.62812083e-03 2.69382391e-02 6.70170784e-02
        1.53745070e-01 2.37187907e-01 1.83968455e-01 1.15637317e-01 0.
        1.32720098e-01</data></histogram></_>
  <_><id>8</id>
    <height>1.1692905426025391e-01</height>
    <contour2d>
      5.53590775e-01 2.02539079e-02 5.34369349e-01 3.01258489e-02
      5.29670298e-01 3.01667359e-02 5.11173189e-01 2.99116364e-03
      5.08849502e-01 -1.21954707e-02 5.08728862e-01 -1.71980597e-02
      5.10688126e-01 -2.06837524e-02 5.30385137e-01 -3.29180174e-02
      5.37181854e-01 -3.42732258e-02 5.56968927e-01 3.27429315e-03
      5.59796810e-01 9.87402257e-03 5.59780538e-01 1.25067709e-02
      5.55853188e-01 1.76907368e-02</contour2d>
    <histogram type_id="opencv-matrix">
      <rows>20</rows>
      <cols>1</cols>
      <dt>f</dt>
      <data>
        4.45906445e-02 3.58187146e-02 1.02339182e-02 0. 0. 0. 0. 0. 0.
        0. 7.30994157e-04 4.38596494e-03 1.31578948e-02 6.65204674e-02
        1.53508767e-01 2.96052635e-01 1.38888896e-01 1.06725149e-01 0.
        1.29385963e-01</data></histogram></_>
  <_><id>9</id>
    <height>1.1563152074813843e-01</height>
    <contour2d>
      5.58552444e-01 1.24747315e-02 5.42366266e-01 2.65668966e-02
      5.39485931e-01 2.66119167e-02 5.23979187e-01 1.59044657e-02
      5.07052064e-01 2.96567567e-03 5.05550742e-01 -8.98273545e-04
      5.05297899e-01 -8.89049750e-03 5.05898118e-01 -1.02550369e-02
      5.20917654e-01 -3.51229496e-02 5.26074708e-01 -3.85920741e-02
      5.27121425e-01 -3.88977043e-02 5.59064984e-01 -7.27150077e-03
      5.59878469e-01 -3.28965764e-03 5.59870243e-01 -1.97331002e-03</contour2d>
    <histogram type_id="opencv-matrix">
      <rows>20</rows>
      <cols>1</cols>
      <dt>f</dt>
      <data>
        3.29949223e-02 2.11505927e-02 5.07614203e-03 0. 0. 0. 0. 0. 0.
        0. 0. 6.76818937e-03 1.35363787e-02 6.42977953e-02
        1.74280882e-01 2.99492389e-01 1.31979689e-01 5.75296097e-02 0.
        1.92893401e-01</data></histogram></_>
  <_><id>10</id>
    <height>1.1483758687973022e-01</height>
    <contour2d>
      5.57663083e-01 -9.85080190e-03 5.57614207e-01 -1.97345251e-03
      5.55516183e-01 2.44677383e-02 5.54479003e-01 2.44613700e-02
      5.10392368e-01 1.44118350e-02 5.06009758e-01 1.05868643e-02
      5.03483415e-01 6.75224280e-03 5.04074693e-01 1.67614839e-03
      5.10450721e-01 -3.33499610e-02 5.18362105e-01 -3.32622193e-02
      5.52185178e-01 -1.63453259e-02 5.56651592e-01 -1.24829123e-02</contour2d>
    <histogram type_id="opencv-matrix">
      <rows>20</rows>
      <cols>1</cols>
      <dt>f</dt>
      <data>
        2.45614033e-02 1.57894734e-02 4.38596494e-03 0. 0. 0. 0. 0. 0.
        0. 0. 4.38596494e-03 2.19298247e-02 8.68421048e-02
        1.94736853e-01 3.22807014e-01 9.91228074e-02 3.33333351e-02 0.
        1.92105263e-01</data></histogram></_>
  <_><id>11</id>
    <height>1.1582124233245850e-01</height>
    <contour2d>
      5.55453002e-01 1.50815733e-02 5.35339236e-01 2.50766389e-02
      5.34329176e-01 2.50704363e-02 5.09496987e-01 1.81102753e-02
      5.08517861e-01 1.68434121e-02 5.06288886e-01 1.30891353e-02
      5.07123590e-01 -2.01348104e-02 5.07505417e-01 -2.34268066e-02
      5.09903550e-01 -2.56050490e-02 5.41703343e-01 -2.39182450e-02
      5.47150195e-01 -2.27330197e-02 5.52201390e-01 -1.89572331e-02
      5.53817630e-01 -1.63612626e-02 5.56643486e-01 -1.11699868e-02
      5.57581663e-01 3.27814743e-03 5.57727814e-01 1.11777419e-02</contour2d>
    <histogram type_id="opencv-matrix">
      <rows>20</rows>
      <cols>1</cols>
      <dt>f</dt>
      <data>
        1.18074482e-02 8.17438681e-03 3.63306096e-03 0. 0. 0. 0. 0. 0.
        0. 0. 7.26612192e-03 2.08900999e-02 8.81017298e-02
        1.77111715e-01 3.25158954e-01 9.53678489e-02 3.99636701e-02 0.
        2.22524986e-01</data></histogram></_>
  <_><id>12</id>
    <height>1.1479038000106812e-01</height>
    <contour2d>
      5.58839798e-01 -1.97963743e-03 5.57793081e-01 6.46781758e-04
      5.55715919e-01 3.26687377e-03 5.22819400e-01 2.60659214e-02
      5.17017841e-01 2.59723179e-02 5.05558729e-01 -2.18341174e-03
      5.04576683e-01 -6.04490517e-03 5.04757643e-01 -1.34399245e-02
      5.05035222e-01 -1.46264257e-02 5.10910153e-01 -1.89017877e-02
      5.39519668e-01 -3.40138562e-02 5.42753756e-01 -3.39939967e-02
      5.48984885e-01 -2.54307408e-02 5.53817630e-01 -1.63612626e-02
      5.57042062e-01 -8.52615107e-03 5.58847964e-01 -3.29598505e-03</contour2d>
    <histogram type_id="opencv-matrix">
      <rows>20</rows>
      <cols>1</cols>
      <dt>f</dt>
      <data>
        1.92307699e-02 2.01923084e-02 5.76923089e-03 9.61538462e-04 0.
        0. 0. 0. 0. 0. 0. 9.61538462e-04 2.11538468e-02 9.61538479e-02
        1.78846151e-01 3.53846163e-01 1.14423074e-01 3.36538479e-02 0.
        1.54807687e-01</data></histogram></_>
  <_><id>13</id>
    <height>1.1644792556762695e-01</height>
    <contour2d>
      5.63059449e-01 -1.77507047e-02 5.63238502e-01 -1.38453320e-02
      5.49738050e-01 1.75572112e-02 5.47482669e-01 2.14021150e-02
      5.38022280e-01 2.65146587e-02 5.35871685e-01 2.65014544e-02
      5.32357097e-01 2.52656378e-02 5.12821376e-01 1.19612003e-02
      5.12565136e-01 1.14049930e-02 5.12279809e-01 7.02892896e-03
      5.12304783e-01 3.00168619e-03 5.12784362e-01 1.66711793e-03
      5.30818582e-01 -3.44086066e-02 5.33621430e-01 -3.78602110e-02
      5.35853624e-01 -3.77459601e-02 5.52258015e-01 -2.80988812e-02
      5.56121349e-01 -2.55774986e-02 5.59791684e-01 -2.16542538e-02</contour2d>
    <histogram type_id="opencv-matrix">
      <rows>20</rows>
      <cols>1</cols>
      <dt>f</dt>
      <data>
        3.96935940e-02 4.24791090e-02 2.29805019e-02 5.57103055e-03
        6.96378818e-04 0. 0. 0. 0. 0. 1.39275764e-03 9.74930357e-03
        1.60167124e-02 6.12813346e-02 1.78969353e-01 2.59749293e-01
        1.30222842e-01 6.54596090e-02 0. 1.65738165e-01</data></histogram></_>
  <_><id>14</id>
    <height>1.1475634574890137e-01</height>
    <contour2d>
      5.55764198e-01 -2.74449643e-02 5.57984829e-01 -2.35617645e-02
      5.59984624e-01 -1.56478435e-02 5.60067832e-01 -1.18018221e-03
      5.52705824e-01 2.37108283e-02 5.51669359e-01 2.50140987e-02
      5.50642967e-01 2.50062235e-02 5.21673977e-01 2.13035904e-02
      5.19178987e-01 2.04003509e-02 5.18793881e-01 1.53002255e-02
      5.24973631e-01 -3.29330824e-02 5.25911212e-01 -3.43273319e-02
      5.29230893e-01 -3.43018547e-02 5.39789200e-01 -3.21884044e-02</contour2d>
    <histogram type_id="opencv-matrix">
      <rows>20</rows>
      <cols>1</cols>
      <dt>f</dt>
      <data>
        3.68349254e-02 4.77489755e-02 2.31923610e-02 6.82128221e-03
        6.82128244e-04 0. 0. 0. 0. 0. 0. 4.77489782e-03 1.56889502e-02
        7.77626187e-02 1.78035468e-01 3.19918156e-01 1.22100957e-01
        4.36562076e-02 0. 1.22783087e-01</data></histogram></_>
  <_><id>15</id>
    <height>1.1470204591751099e-01</height>
    <contour2d>
      5.58519900e-01 1.77263059e-02 5.42374253e-01 2.52679158e-02
      5.32957196e-01 2.89332010e-02 5.32333493e-01 2.88301036e-02
      5.27809381e-01 2.68961806e-02 5.26611805e-01 2.54080500e-02
      5.14319777e-01 -2.56436002e-02 5.15200257e-01 -2.65023205e-02
      5.25932431e-01 -3.23144905e-02 5.36717057e-01 -3.42718437e-02
      5.38737178e-01 -3.42594422e-02 5.43152571e-01 -3.31360735e-02
      5.46970010e-01 -2.93506775e-02 5.51187158e-01 -2.02694386e-02
      5.57622313e-01 -3.28632724e-03 5.60851753e-01 5.93125680e-03
      5.60819149e-01 1.11967223e-02</contour2d>
    <histogram type_id="opencv-matrix">
      <rows>20</rows>
      <cols>1</cols>
      <dt>f</dt>
      <data>
        4.07017544e-02 5.33333346e-02 2.10526325e-02 2.10526329e-03 0.
        0. 0. 0. 0. 0. 0. 7.01754412e-04 1.47368424e-02 9.19298306e-02
        1.68421060e-01 2.92631596e-01 1.55789480e-01 5.47368452e-02 0.
        1.03859656e-01</data></histogram></_>
  <_><id>16</id>
    <height>1.1713296175003052e-01</height>
    <contour2d>
      5.50753117e-01 3.11667435e-02 5.49660206e-01 3.11600324e-02
      5.40248871e-01 2.94081327e-02 5.11248708e-01 2.35854764e-04
      5.09799957e-01 -5.86804841e-03 5.10036111e-01 -1.02296276e-02
      5.11145055e-01 -1.29075823e-02 5.21970212e-01 -3.05006765e-02
      5.24093151e-01 -3.25642005e-02 5.29304504e-01 -3.28328237e-02
      5.35308242e-01 -2.89456993e-02 5.51171005e-01 -1.76575314e-02
      5.62969685e-01 -3.27067589e-03 5.62928915e-01 3.31116468e-03
      5.59991121e-01 1.24713173e-02</contour2d>
    <histogram type_id="opencv-matrix">
      <rows>20</rows>
      <cols>1</cols>
      <dt>f</dt>
      <data>
        2.59109307e-02 4.04858291e-02 5.66801615e-03 0. 0. 0. 0. 0. 0.
        0. 0. 2.42914981e-03 1.53846154e-02 6.39676079e-02
        1.91902831e-01 3.28744948e-01 1.03643723e-01 3.07692308e-02 0.
        1.91093117e-01</data></histogram></_></obj>
</opencv_storage>
